astrolaza/__init__.py
astrolaza/packages.py
astrolaza/LazaBin/__init__.py
astrolaza/LazaBin/binning.py
astrolaza/LazaFlux/SED.py
astrolaza/LazaFlux/__init__.py
astrolaza/LazaFlux/mags.py
astrolaza/LazaGal/UV.py
astrolaza/LazaGal/__init__.py
astrolaza/LazaGal/attenuation.py
astrolaza/LazaGal/mass.py
astrolaza/LazaGal/surface.py
astrolaza/LazaMaps/__init__.py
astrolaza/LazaMaps/mapping.py
astrolaza/LazaMaps/movies.py
astrolaza/LazaPipes/__init__.py
astrolaza/LazaPipes/corrections.py
astrolaza/LazaPipes/data_handling.py
astrolaza/LazaPipes/fitting.py
astrolaza/LazaPipes/plotting.py
astrolaza/LazaUtils/MPF.py
astrolaza/LazaUtils/__init__.py
astrolaza/LazaUtils/get.py
astrolaza/LazaVars/__init__.py
astrolaza/LazaVars/dics.py
astrolaza-0.0.40.dist-info/licenses/LICENSE
astrolaza-0.0.40.dist-info/METADATA
astrolaza-0.0.40.dist-info/WHEEL
astrolaza-0.0.40.dist-info/top_level.txt
astrolaza-0.0.40.dist-info/RECORD
