Metadata-Version: 2.4
Name: astrolaza
Version: 0.0.40
Author: A. Laza-Ramos
Author-email: andres.laza@uv.es
Classifier: Programming Language :: Python :: 3
Classifier: License :: OSI Approved :: MIT License
Classifier: Operating System :: OS Independent
License-File: LICENSE
Requires-Dist: numpy>=2.1.0
Requires-Dist: matplotlib>=3.8.0
Requires-Dist: bagpipes>=1.1.0
Requires-Dist: scipy>=1.15.0
Requires-Dist: astropy>=7.0.1
Requires-Dist: natsort>=8.4
Requires-Dist: moviepy>=2.0.0
Dynamic: author
Dynamic: author-email
Dynamic: classifier
Dynamic: license-file
Dynamic: requires-dist
